[
    {
        "question": "甲對乙下藥，使其陷入昏迷狀態後對其性交。甲的行為應如何論處？《模擬》",
        "options": [
            "成立普通強制性交罪 (第221條)",
            "成立加重強制性交罪 (第222條)",
            "成立乘機性交罪 (第225條)",
            "僅成立傷害罪"
        ],
        "answer": 1,
        "explanation": "依刑法第222條第1項第4款，以藥劑犯強制性交罪者，為加重強制性交罪。"
    },
    {
        "question": "甲對15歲的少年乙為猥褻之行為。甲的行為成立何罪？《模擬》",
        "options": [
            "強制猥褻罪 (第224條)",
            "乘機猥褻罪 (第225條)",
            "對於男女為猥褻行為罪 (第227條第4項)",
            "不構成犯罪，因已滿14歲"
        ],
        "answer": 2,
        "explanation": "依刑法第227條第4項規定，對於十四歲以上未滿十六歲之男女為猥褻之行為者，成立本罪。"
    },
    {
        "question": "醫生甲利用為病患乙看診的機會，對乙為猥褻行為。甲的行為除了強制猥褻罪外，可能因其身分而觸犯何罪？《模擬》",
        "options": [
            "業務上過失罪",
            "利用權勢猥褻罪 (第228條)",
            "背信罪",
            "沒有其他加重規定"
        ],
        "answer": 1,
        "explanation": "依刑法第228條第2項，對於因醫療等關係受自己監督、扶助、照護之人，利用機會為猥褻之行為者，成立本罪。"
    },
    {
        "question": "下列何種罪名，依刑法第229-1條規定，屬於告訴乃論之罪？《模擬》",
        "options": [
            "對未滿14歲之人為性交",
            "加重強制性交罪",
            "對配偶犯強制性交罪",
            "乘機性交罪"
        ],
        "answer": 2,
        "explanation": "依刑法第229-1條規定，對配偶犯第二百二十一條（強制性交）、第二百二十四條（強制猥褻）之罪者，須告訴乃論。"
    },
    {
        "question": "甲犯下強制性交罪，並在過程中持手機錄下被害人的影像。甲的錄影行為，屬於下列何種加重事由？《模擬》",
        "options": [
            "施以凌虐",
            "攜帶兇器",
            "對被害人為照相、錄音、錄影",
            "不屬於加重事由"
        ],
        "answer": 2,
        "explanation": "依刑法第222條第1項第9款規定，對被害人為照相、錄音、錄影或散布、播送該影像、聲音、電磁紀錄，為加重強制性交之事由。"
    }
]