[
    {
        "question": "法官在量刑時，考量被告的「智識程度」，是依據刑法哪一條的規定？《模擬》",
        "options": [
            "第57條",
            "第59條",
            "第61條",
            "第62條"
        ],
        "answer": 0,
        "explanation": "依刑法第57條第6款，犯罪行為人之智識程度，為科刑時應審酌之事項之一。"
    },
    {
        "question": "甲因詐欺取得不法利益1000萬元，但其所犯罪名之罰金最高額僅為50萬元。法院在科處罰金時應如何處理？《模擬》",
        "options": [
            "最高只能科處50萬元罰金",
            "得於所得利益1000萬元之範圍內酌量加重罰金",
            "應另外宣告沒收犯罪所得，不得加重罰金",
            "應將罰金與沒收合併計算"
        ],
        "answer": 1,
        "explanation": "依刑法第58條後段規定，如所得之利益超過罰金最多額時，得於所得利益之範圍內酌量加重。"
    },
    {
        "question": "甲因犯竊盜罪（最重本刑5年），情節輕微顯可憫恕，法院依第59條酌量減輕其刑後，認為仍嫌過重。法院下一步可能如何處理？《模擬》",
        "options": [
            "依第61條免除其刑",
            "再次依第59條減輕其刑",
            "改判無罪",
            "宣告緩刑"
        ],
        "answer": 0,
        "explanation": "依刑法第61條第2款，竊盜罪若情節輕微，顯可憫恕，認為依第59條減輕其刑仍嫌過重者，得免除其刑。"
    },
    {
        "question": "甲犯A罪，依法得減輕其刑；又因其為幫助犯，依法亦得減輕其刑。若法院決定兩者皆適用，應如何計算？《模擬》",
        "options": [
            "先依較多之數減輕",
            "先依較少之數減輕",
            "兩者取其一適用即可",
            "將兩種減輕比例相加後減輕"
        ],
        "answer": 1,
        "explanation": "依刑法第71條第2項規定，有二種以上之減輕者，先依較少之數減輕之。"
    },
    {
        "question": "若有期徒刑依法加重及減輕，其計算結果有不滿一日之畸零時間，應如何處理？《模擬》",
        "options": [
            "四捨五入",
            "無條件進位",
            "無條件捨去（不算）",
            "由法官裁量"
        ],
        "answer": 2,
        "explanation": "依刑法第72條規定，因刑之加重、減輕，而有不滿一日之時間或不滿一元之額數者，不算。"
    }
]