[
    {
        "question": "甲犯下最重本刑為「一年未滿有期徒刑」之罪，其追訴權時效為多久？《模擬》",
        "options": [
            "三年",
            "五年",
            "七年",
            "十年"
        ],
        "answer": 1,
        "explanation": "依刑法第80條第1項第4款規定，犯最重本刑為一年未滿有期徒刑、拘役或罰金之罪者，其追訴權時效為五年。"
    },
    {
        "question": "甲被判處有期徒刑2年確定，依法其行刑權時效為多久？《模擬》",
        "options": [
            "七年",
            "十年",
            "十五年",
            "三十年"
        ],
        "answer": 2,
        "explanation": "依刑法第84條第1項第3款規定，宣告一年以上三年未滿有期徒刑者，其行刑權時效為十五年。"
    },
    {
        "question": "追訴權時效的起算點，在「繼續犯」的場合應如何決定？《模擬》",
        "options": [
            "自犯罪行為著手之日起算",
            "自犯罪結果發生之日起算",
            "自犯罪行為終了之日起算",
            "自被害人提告之日起算"
        ],
        "answer": 2,
        "explanation": "依刑法第80條第2項但書規定，犯罪行為有繼續之狀態者，自行為終了之日起算。"
    },
    {
        "question": "甲因A罪被提起公訴，審理期間長達10年。A罪的法定追訴權時效為20年。此時A罪的追訴權時效是否消滅？《模擬》",
        "options": [
            "消滅，因已過10年",
            "不消滅，因起訴會導致時效停止進行",
            "消滅，因審理過久",
            "不消滅，但應重新計算時效"
        ],
        "answer": 1,
        "explanation": "依刑法§83 I，追訴權時效因起訴而「停止進行」。但依§83 II第2款，若審判程序不能開始或繼續，其停止期間已達原時效期間三分之一者，停止原因視為消滅。本案中，審理持續進行，時效處於停止狀態。"
    },
    {
        "question": "甲被判處罰金5萬元確定，但其遲未繳納。其行刑權時效為多久？《模擬》",
        "options": [
            "三年",
            "五年",
            "七年",
            "十年"
        ],
        "answer": 2,
        "explanation": "依刑法第84條第1項第4款規定，宣告一年未滿有期徒刑、拘役或「罰金」者，其行刑權時效為七年。"
    }
]